mtl10/__init__.py
mtl10/color_combos.py
mtl10/info.py
mtl10/motley.py
mtl10-0.1.0.dist-info/METADATA
mtl10-0.1.0.dist-info/WHEEL
mtl10-0.1.0.dist-info/RECORD
