Metadata-Version: 2.1
Name: mtl10
Version: 0.1.0
Summary: 
Author: Макс
Author-email: rumyantsev1m0s1@gmail.com
Requires-Python: >=3.12,<4.0
Classifier: Programming Language :: Python :: 3
Classifier: Programming Language :: Python :: 3.12
Classifier: Programming Language :: Python :: 3.13
Requires-Dist: colorama (>=0.4.6,<0.5.0)
Requires-Dist: twine (>=6.0.1,<7.0.0)
